__init__.py
arnet.py
arnet-0.0.1.dist-info/LICENSE
arnet-0.0.1.dist-info/METADATA
arnet-0.0.1.dist-info/WHEEL
arnet-0.0.1.dist-info/top_level.txt
arnet-0.0.1.dist-info/RECORD
