Metadata-Version: 2.1
Name: arnet
Version: 0.0.1
Summary: Nonlinear autoregression with feed-forward neural networks (or any estimator really)
Author: Mustafa Aydın
Project-URL: Source code, https://github.com/mustafaaydn/arnet
Keywords: time series,autoregression,neural networks,prediction
Classifier: Programming Language :: Python :: 3
Classifier: License :: OSI Approved :: Artistic License
Classifier: Operating System :: OS Independent
Requires-Python: >=3.8
License-File: LICENSE
Requires-Dist: numpy >=1.22.0
Requires-Dist: pandas >=1.4.0
Requires-Dist: scikit-learn
Requires-Dist: statsmodels
